odoo/addons/pos_customer_display/README.rst
odoo/addons/pos_customer_display/__init__.py
odoo/addons/pos_customer_display/__manifest__.py
odoo/addons/pos_customer_display/i18n/de.po
odoo/addons/pos_customer_display/i18n/es.po
odoo/addons/pos_customer_display/i18n/fr.po
odoo/addons/pos_customer_display/i18n/hr_HR.po
odoo/addons/pos_customer_display/i18n/it.po
odoo/addons/pos_customer_display/i18n/nl.po
odoo/addons/pos_customer_display/i18n/nl_NL.po
odoo/addons/pos_customer_display/i18n/pos_customer_display.pot
odoo/addons/pos_customer_display/models/__init__.py
odoo/addons/pos_customer_display/models/pos_config.py
odoo/addons/pos_customer_display/readme/CONFIGURE.rst
odoo/addons/pos_customer_display/readme/CONTRIBUTORS.rst
odoo/addons/pos_customer_display/readme/DESCRIPTION.rst
odoo/addons/pos_customer_display/readme/INSTALL.rst
odoo/addons/pos_customer_display/readme/ROADMAP.rst
odoo/addons/pos_customer_display/readme/USAGE.rst
odoo/addons/pos_customer_display/static/description/icon.png
odoo/addons/pos_customer_display/static/description/index.html
odoo/addons/pos_customer_display/static/src/js/chrome.js
odoo/addons/pos_customer_display/static/src/js/customer_display_2_20.js
odoo/addons/pos_customer_display/static/src/js/devices.js
odoo/addons/pos_customer_display/static/src/js/gui.js
odoo/addons/pos_customer_display/static/src/js/models.js
odoo/addons/pos_customer_display/static/src/js/screens.js
odoo/addons/pos_customer_display/views/assets.xml
odoo/addons/pos_customer_display/views/view_pos_config.xml
odoo12_addon_pos_customer_display-12.0.1.1.2.dist-info/METADATA
odoo12_addon_pos_customer_display-12.0.1.1.2.dist-info/WHEEL
odoo12_addon_pos_customer_display-12.0.1.1.2.dist-info/top_level.txt
odoo12_addon_pos_customer_display-12.0.1.1.2.dist-info/RECORD
